SpringSecurity512ReleaseZhongwenWendang/README.md
SpringSecurity512ReleaseZhongwenWendang/__init__.py
SpringSecurity512ReleaseZhongwenWendang/__main__.py
SpringSecurity512ReleaseZhongwenWendang/file.epub
SpringSecurity512ReleaseZhongwenWendang/index.html
SpringSecurity512ReleaseZhongwenWendang/css/__init__.py
SpringSecurity512ReleaseZhongwenWendang/css/annotations.css
SpringSecurity512ReleaseZhongwenWendang/css/main.css
SpringSecurity512ReleaseZhongwenWendang/css/normalize.css
SpringSecurity512ReleaseZhongwenWendang/css/popup.css
SpringSecurity512ReleaseZhongwenWendang/font/__init__.py
SpringSecurity512ReleaseZhongwenWendang/font/fontello.eot
SpringSecurity512ReleaseZhongwenWendang/font/fontello.svg
SpringSecurity512ReleaseZhongwenWendang/font/fontello.ttf
SpringSecurity512ReleaseZhongwenWendang/font/fontello.woff
SpringSecurity512ReleaseZhongwenWendang/img/__init__.py
SpringSecurity512ReleaseZhongwenWendang/img/annotator-glyph-sprite.png
SpringSecurity512ReleaseZhongwenWendang/img/annotator-icon-sprite.png
SpringSecurity512ReleaseZhongwenWendang/img/apple-touch-icon.png
SpringSecurity512ReleaseZhongwenWendang/img/cancelfullscreen.png
SpringSecurity512ReleaseZhongwenWendang/img/close.png
SpringSecurity512ReleaseZhongwenWendang/img/fullscreen.png
SpringSecurity512ReleaseZhongwenWendang/img/loader.gif
SpringSecurity512ReleaseZhongwenWendang/img/menu-icon.png
SpringSecurity512ReleaseZhongwenWendang/img/save.png
SpringSecurity512ReleaseZhongwenWendang/img/saved.png
SpringSecurity512ReleaseZhongwenWendang/img/settings-s.png
SpringSecurity512ReleaseZhongwenWendang/img/settings.png
SpringSecurity512ReleaseZhongwenWendang/img/star.png
SpringSecurity512ReleaseZhongwenWendang/js/__init__.py
SpringSecurity512ReleaseZhongwenWendang/js/epub.js
SpringSecurity512ReleaseZhongwenWendang/js/epub.min.js
SpringSecurity512ReleaseZhongwenWendang/js/epub.min.map
SpringSecurity512ReleaseZhongwenWendang/js/hooks.min.js
SpringSecurity512ReleaseZhongwenWendang/js/hooks.min.map
spring_security_5_1_2_release_zhongwen_wendang-2024.3.5.0.dist-info/METADATA
spring_security_5_1_2_release_zhongwen_wendang-2024.3.5.0.dist-info/WHEEL
spring_security_5_1_2_release_zhongwen_wendang-2024.3.5.0.dist-info/entry_points.txt
spring_security_5_1_2_release_zhongwen_wendang-2024.3.5.0.dist-info/top_level.txt
spring_security_5_1_2_release_zhongwen_wendang-2024.3.5.0.dist-info/RECORD
